[
  {
    "id": "5edc459f-2152-488b-b8d6-a85d7a79437a",
    "first_name": "Gustavo",
    "last_name": "Zanini",
    "email": "gustavodev25@gmail.com",
    "phone": "(18) 99623-9335",
    "password_hash": "$2b$10$A3WK8hS7SXpcBPYu7HGrxOPWiJ9U7Y9hpUvF8YZFKOBUGMNYvi.Qe",
    "created_at": "2025-11-26T17:43:45.602751+00:00",
    "updated_at": "2025-12-05T18:05:31.198583+00:00",
    "last_login": "2025-12-05T18:05:30.781+00:00",
    "is_active": true,
    "is_admin": true,
    "created_by_admin": false,
    "admin_generated_password": null
  },
  {
    "id": "91d6b6ce-3568-4a24-aa90-51622dccc579",
    "first_name": "HELLEN",
    "last_name": "PRADO",
    "email": "pradohellen@yahoo.com.br",
    "phone": "(11) 97022-4969",
    "password_hash": "$2b$10$iQGKoMLpzkvyBBZmMeFWauro1ONov5O25LNXK0KyAweNfcwVB3Pke",
    "created_at": "2025-12-09T22:12:40.634901+00:00",
    "updated_at": "2025-12-09T22:13:32.07138+00:00",
    "last_login": "2025-12-09T22:13:31.897+00:00",
    "is_active": true,
    "is_admin": false,
    "created_by_admin": true,
    "admin_generated_password": "yjv4i09c"
  },
  {
    "id": "c6c01d31-1db5-4e42-864c-22ea5e62d54e",
    "first_name": "Tim",
    "last_name": "!",
    "email": "acessopcvictor@gmail.com",
    "phone": "(11) 99173-0939",
    "password_hash": "$2b$10$6mRxUBmOCuh/A8u8UZiDiOvR/9ybIfyWRrrlS2IpC5C2PaSalFT/u",
    "created_at": "2025-12-04T20:32:17.021543+00:00",
    "updated_at": "2026-01-06T19:20:15.798+00:00",
    "last_login": "2026-01-07T03:56:20.85+00:00",
    "is_active": true,
    "is_admin": true,
    "created_by_admin": true,
    "admin_generated_password": "7c78tnt0"
  },
  {
    "id": "ed699232-3121-45dc-b1bf-99fccaac6797",
    "first_name": "BRUNA",
    "last_name": "CASTRO",
    "email": "bcastro.bc14@outlook.com",
    "phone": "(11) 96139-9517",
    "password_hash": "$2b$10$.qc0SZbzGJH2ZRexItIhmeejCXRIcXfVpiz8Z5N43AKbkGTJZhVZK",
    "created_at": "2025-12-09T20:27:31.691478+00:00",
    "updated_at": "2025-12-09T20:27:31.691478+00:00",
    "last_login": "2026-01-05T15:33:31.217+00:00",
    "is_active": true,
    "is_admin": false,
    "created_by_admin": true,
    "admin_generated_password": "38ihgshj"
  },
  {
    "id": "3a81b3e3-dfb2-4f5e-adac-b71975353599",
    "first_name": "GUILHERME",
    "last_name": "GOUVEIA",
    "email": "guigf2007@gmail.com",
    "phone": "(11) 94142-8809",
    "password_hash": "$2b$10$xuP99y/39JFQZjyISxm6IeNDIyxBV8nI4uUpShsJt/ypJwOXcMAhO",
    "created_at": "2025-12-09T20:18:47.331702+00:00",
    "updated_at": "2025-12-10T01:47:20.16023+00:00",
    "last_login": "2026-01-05T18:42:27.621+00:00",
    "is_active": true,
    "is_admin": false,
    "created_by_admin": true,
    "admin_generated_password": "gs6p40xg"
  },
  {
    "id": "3474b760-cdbb-455b-8dd2-f4cd6ec46f0e",
    "first_name": "LAIS",
    "last_name": "MIRANDA",
    "email": "laismrd93@gmail.com",
    "phone": "(11) 94548-7644",
    "password_hash": "$2b$10$2OcywadQo.3Mlj5TyPbb5.2XJ5hnctFuMvMMt4FQQfPqAuAMrbI7S",
    "created_at": "2025-12-09T20:29:40.839496+00:00",
    "updated_at": "2025-12-09T20:35:08.458107+00:00",
    "last_login": "2026-01-06T12:02:02.346+00:00",
    "is_active": true,
    "is_admin": false,
    "created_by_admin": true,
    "admin_generated_password": "c3zlpd18"
  },
  {
    "id": "dd90527d-d3dc-45ee-93fe-bad81a2298b2",
    "first_name": "KAWAM",
    "last_name": "BUENO",
    "email": "kawam.bueno@gmail.com",
    "phone": "(11) 98219-5773",
    "password_hash": "$2b$10$od26ti1eKrZgtvT/ERsU1Ohz61SsDKQ/1n7TrJyzsSGNL0T9F4UGW",
    "created_at": "2025-12-09T20:34:31.954891+00:00",
    "updated_at": "2025-12-09T20:42:45.925592+00:00",
    "last_login": "2026-01-06T12:48:01.477+00:00",
    "is_active": true,
    "is_admin": false,
    "created_by_admin": true,
    "admin_generated_password": "r9rmwi7i"
  },
  {
    "id": "42b6c7ba-bef7-4dc2-b1eb-45170f2bb8e7",
    "first_name": "THALITA",
    "last_name": "ALEIXO",
    "email": "thalitapassareli@hotmail.com",
    "phone": "(11) 99579-2055",
    "password_hash": "$2b$10$.2qyL9KyIZ9Hipq1yBinLOaY8kXI.rPPAKIs68NFpR3oqk3xIAlcS",
    "created_at": "2025-12-09T20:16:27.547695+00:00",
    "updated_at": "2025-12-09T20:20:13.862202+00:00",
    "last_login": "2026-01-06T14:06:29.407+00:00",
    "is_active": true,
    "is_admin": false,
    "created_by_admin": true,
    "admin_generated_password": "irxmh0zw"
  },
  {
    "id": "1dbc54de-992d-435f-a99c-388349d470f2",
    "first_name": "BEATRIZ OLIVEIRA",
    "last_name": "OLIVEIRA",
    "email": "bia37807@outlook.com",
    "phone": "(11) 95833-2193",
    "password_hash": "$2b$10$1Ri2lGPSSJeiWmmK.cgiHeJRI7n1aVE5XJgqhLt89txArsUqxGlQ.",
    "created_at": "2025-12-09T20:24:52.282381+00:00",
    "updated_at": "2025-12-10T11:40:22.012824+00:00",
    "last_login": "2026-01-06T21:06:31.644+00:00",
    "is_active": true,
    "is_admin": false,
    "created_by_admin": true,
    "admin_generated_password": "0d7f77w4"
  },
  {
    "id": "bd14cd9c-cfff-4311-b547-74d1d9363269",
    "first_name": "ANA",
    "last_name": "SANTOS",
    "email": "ana@gmail.com",
    "phone": "(11) 9999-9999",
    "password_hash": "$2b$10$7Me6oqxBFZHQebzjkVq3pOOe2Q3bSOmGelurZ5EvpGtrOQbydranS",
    "created_at": "2026-01-02T21:14:58.54725+00:00",
    "updated_at": "2026-01-02T21:14:58.54725+00:00",
    "last_login": null,
    "is_active": true,
    "is_admin": false,
    "created_by_admin": true,
    "admin_generated_password": "sft5hwv8"
  },
  {
    "id": "c97a34e6-4d0e-4b74-b346-ffce0cb06a8a",
    "first_name": "LAISA",
    "last_name": "SILVA MIRANDA",
    "email": "laisaerhard@gmail.com",
    "phone": "(11) 94584-5823",
    "password_hash": "$2b$10$0LSKEzzwVq5gIizHy1eexe4JK7yEVBAvZsmTreA4MiUg.UyLVcX9i",
    "created_at": "2025-12-09T13:35:38.168567+00:00",
    "updated_at": "2025-12-09T13:35:38.168567+00:00",
    "last_login": "2026-01-06T22:40:07.671+00:00",
    "is_active": true,
    "is_admin": false,
    "created_by_admin": true,
    "admin_generated_password": "1kz6juqw"
  },
  {
    "id": "ddc255fe-9be0-418c-90bb-7a16f63ae5ad",
    "first_name": "MARIA",
    "last_name": "VITÓRIA",
    "email": "viviistatkevicius@gmail.com",
    "phone": "(11) 97656-0683",
    "password_hash": "$2b$10$22tuocMHJ.Ob8ngd6d0U8.ixoG3JspFqLLZHhYOGAShOfRjQ39dE2",
    "created_at": "2025-12-09T20:33:03.625587+00:00",
    "updated_at": "2025-12-10T11:18:41.52468+00:00",
    "last_login": "2025-12-13T01:54:10.451+00:00",
    "is_active": true,
    "is_admin": false,
    "created_by_admin": true,
    "admin_generated_password": "yaa0d29i"
  },
  {
    "id": "ca92e16e-faf8-4e73-9bb5-3f5cf7667a00",
    "first_name": "EVELLYN",
    "last_name": "PRADO",
    "email": "evellyn@gmail.com",
    "phone": "(11) 99999-9999",
    "password_hash": "$2b$10$UNfAgZxEwo5MxBxt5hZ1Ee/D22WWZG/GOctlyfJubPiby60rYFuBW",
    "created_at": "2026-01-02T21:15:44.635049+00:00",
    "updated_at": "2026-01-02T21:15:44.635049+00:00",
    "last_login": null,
    "is_active": true,
    "is_admin": false,
    "created_by_admin": true,
    "admin_generated_password": "89vym84p"
  },
  {
    "id": "3e73a157-be0a-4026-ae70-f8004b831593",
    "first_name": "OUTROS",
    "last_name": ".",
    "email": "outros@gmail.com",
    "phone": "(11) 99999-9999",
    "password_hash": "$2b$10$dNEvJFWED/sV80utzN2gu.zxVQ2oK2bpRyUPmguDDvllYdyF7EgHC",
    "created_at": "2026-01-02T21:16:27.295851+00:00",
    "updated_at": "2026-01-02T21:16:27.295851+00:00",
    "last_login": null,
    "is_active": true,
    "is_admin": false,
    "created_by_admin": true,
    "admin_generated_password": "in4yoo3c"
  },
  {
    "id": "51cbe1f7-0c68-47e0-a565-1ad4aa09f680",
    "first_name": "Gianlucca",
    "last_name": "Florencio",
    "email": "gianlucca.florencio@zeroholding.com.br",
    "phone": "(11) 99002-1212",
    "password_hash": "$2b$10$Vhm8Y9yttYWmAv/Uz8CZROoKiytGYXW48SC/uTUd1z8z03J/m/R5a",
    "created_at": "2025-12-01T12:34:02.085247+00:00",
    "updated_at": "2025-12-11T12:12:51.199715+00:00",
    "last_login": "2026-01-06T22:40:24.409+00:00",
    "is_active": true,
    "is_admin": true,
    "created_by_admin": true,
    "admin_generated_password": null
  }
]